tests/__init__.py
tests/test_functional.py
weighslide/__init__.py
weighslide/weighslide.py
weighslide-0.2.5.dist-info/LICENSE.txt
weighslide-0.2.5.dist-info/METADATA
weighslide-0.2.5.dist-info/WHEEL
weighslide-0.2.5.dist-info/top_level.txt
weighslide-0.2.5.dist-info/RECORD
