Metadata-Version: 2.1
Name: weighslide
Version: 0.2.5
Summary: Flexible sliding window analysis
Home-page: https://github.com/teese/weighslide
Author: Mark Teese
Author-email: mark.teese@SeeImageBelow.de
License: MIT
Download-URL: https://github.com/teese/weighslide/archive/0.2.5.tar.gz
Project-URL: LangoschLab, http://cbp.wzw.tum.de/index.php?id=9
Project-URL: TU_Muenchen, https://www.tum.de
Keywords: sliding data normalisation normalization array
Platform: UNKNOWN
Classifier: Intended Audience :: Science/Research
Classifier: License :: OSI Approved :: MIT License
Classifier: Programming Language :: Python :: 3.6
Classifier: Topic :: Scientific/Engineering :: Bio-Informatics
Requires-Dist: pandas
Requires-Dist: numpy
Requires-Dist: matplotlib
Requires-Dist: pytest
